{
  "id": "ad4a3e80d093cb75",
  "slug": "k187-web-store",
  "name": "k187-web-store",
  "path": "C:\\Users\\nk187\\Downloads\\Projects\\k187 web store",
  "source": "local",
  "category": "web-app",
  "stack": [
    "node",
    "npm",
    "vite"
  ],
  "description": "K187 Bot Store — autonomous trading bots storefront",
  "sizeBytes": 169020,
  "fileCount": 13,
  "hasGit": false,
  "hasReadme": true,
  "hasEnv": false,
  "hasTests": false,
  "hasDocker": false,
  "hasCi": false,
  "hasDeployGuide": true,
  "hasBuildArtifacts": false,
  "lastModified": "2026-05-31T07:33:40.156Z",
  "firstSeen": "2026-06-08T18:49:16.406Z",
  "completionScore": 30,
  "deployScore": 30,
  "healthScore": 70,
  "compositeScore": 38,
  "status": "active",
  "tags": [],
  "createdAt": "2026-06-08T18:49:16.406Z",
  "updatedAt": "2026-06-08T18:49:16.406Z"
}
